setup.py
evilshield/__init__.py
evilshield/utils.py
evilshield-0.0.9.dist-info/LICENSE
evilshield-0.0.9.dist-info/METADATA
evilshield-0.0.9.dist-info/WHEEL
evilshield-0.0.9.dist-info/top_level.txt
evilshield-0.0.9.dist-info/RECORD
