Metadata-Version: 2.1
Name: evilshield
Version: 0.0.9
Summary: This is test
Classifier: Programming Language :: Python :: 3
Classifier: License :: OSI Approved :: MIT License
Classifier: Operating System :: OS Independent
Requires-Python: >=3.6
License-File: LICENSE
